README.md
pyproject.toml
rss_reader.py
setup.py
cool_project/__init__.py
cool_project/cervices/__init__.py
cool_project/cervices/data_output.py
cool_project/cervices/decorators.py
cool_project/cervices/print_functions.py
cool_project/conversion_to_format/__init__.py
cool_project/conversion_to_format/conversion_to_html.py
cool_project/conversion_to_format/conversion_to_pdf.py
cool_project/data_storage/__init__.py
cool_project/data_storage/storage_managers.py
cool_project/data_storage/working_with_storage.py
cool_project/serializers/__init__.py
cool_project/serializers/serializers.py
rss_readerCLI.egg-info/PKG-INFO
rss_readerCLI.egg-info/SOURCES.txt
rss_readerCLI.egg-info/dependency_links.txt
rss_readerCLI.egg-info/entry_points.txt
rss_readerCLI.egg-info/requires.txt
rss_readerCLI.egg-info/top_level.txt
tests/__init__.py
tests/conftest.py
tests/test_data_storage/__init__.py
tests/test_data_storage/test_storage_managers.py
tests/test_data_storage/test_working_with_storage.py
tests/test_rss_reader/__init__.py
tests/test_rss_reader/test_rss_reader.py
tests/tests_conversion_to_format/__init__.py
tests/tests_conversion_to_format/test_conversion_to_html.py
tests/tests_conversion_to_format/test_conversion_to_pdf.py
tests/tests_serializers/__init__.py
tests/tests_serializers/test_serializers.py
tests/tests_services/__init__.py
tests/tests_services/test_data_output.py
tests/tests_services/test_decorators.py
tests/tests_services/test_print_functions.py