Metadata-Version: 2.1
Name: rss-readerCLI
Version: 5.0.0
Summary: Python reader for RSS feed
Home-page: https://github.com/Aleksey-Mikh/Homework/tree/final_task
Author: Aleksey Mikhalkevich
Author-email: lehado67@gmail.com
License: UNKNOWN
Platform: UNKNOWN
Requires-Python: >=3.9
